LICENSE.txt
README.md
pyproject.toml
setup.py
src/lhc/__init__.py
src/lhc/cli/__init__.py
src/lhc/cli/alignments/__init__.py
src/lhc/cli/alignments/__main__.py
src/lhc/cli/alignments/cs_to_table.py
src/lhc/cli/alignments/mismatch_filter.py
src/lhc/cli/alignments/strand.py
src/lhc/cli/loci/__init__.py
src/lhc/cli/loci/__main__.py
src/lhc/cli/loci/closest.py
src/lhc/cli/loci/deduplicate.py
src/lhc/cli/loci/difference.py
src/lhc/cli/loci/extend.py
src/lhc/cli/loci/filter.py
src/lhc/cli/loci/flank.py
src/lhc/cli/loci/generate.py
src/lhc/cli/loci/intersect.py
src/lhc/cli/loci/kmer_filter.py
src/lhc/cli/loci/stats.py
src/lhc/cli/loci/union.py
src/lhc/cli/loci/view.py
src/lhc/cli/multiple_alignments/__init__.py
src/lhc/cli/multiple_alignments/__main__.py
src/lhc/cli/multiple_alignments/align_pairwise.py
src/lhc/cli/multiple_alignments/call_variants.py
src/lhc/cli/multiple_alignments/extract.py
src/lhc/cli/multiple_alignments/get_consensus.py
src/lhc/cli/multiple_alignments/trim_gaps.py
src/lhc/cli/sequences/__init__.py
src/lhc/cli/sequences/__main__.py
src/lhc/cli/sequences/barcode_filter.py
src/lhc/cli/sequences/barcode_split.py
src/lhc/cli/sequences/extract.py
src/lhc/cli/sequences/filter.py
src/lhc/cli/sequences/interleave.py
src/lhc/cli/sequences/reverse_complement.py
src/lhc/cli/sequences/rmdup.py
src/lhc/cli/sequences/split.py
src/lhc/cli/sequences/stat_.py
src/lhc/cli/sequences/unique.py
src/lhc/cli/sequences/view.py
src/lhc/cli/variants/__init__.py
src/lhc/cli/variants/__main__.py
src/lhc/cli/variants/annotate.py
src/lhc/cli/variants/compare.py
src/lhc/cli/variants/diff.py
src/lhc/cli/variants/filter.py
src/lhc/cli/variants/merge.py
src/lhc/cli/variants/sample.py
src/lhc/cli/variants/shift.py
src/lhc/cli/variants/split_alt.py
src/lhc/cli/variants/trim_alt.py
src/lhc/collections/__init__.py
src/lhc/collections/interval_set.py
src/lhc/collections/one_pass_interval_set.py
src/lhc/collections/sequence_set.py
src/lhc/collections/tabix_file_wrapper.py
src/lhc_python.egg-info/PKG-INFO
src/lhc_python.egg-info/SOURCES.txt
src/lhc_python.egg-info/dependency_links.txt
src/lhc_python.egg-info/requires.txt
src/lhc_python.egg-info/top_level.txt
