Metadata-Version: 2.1
Name: lhc-python
Version: 2.5.1
Summary: My personal package for bioinformatics related stuff
Author-email: "Liam H. Childs" <liam.h.childs@gmail.com>
License: GNU GENERAL PUBLIC LICENSE
Project-URL: Homepage, https://github.com/childsish/lhc-python
Classifier: License :: OSI Approved :: MIT License
Classifier: Programming Language :: Python
Classifier: Programming Language :: Python :: 3
Classifier: Development Status :: 4 - Beta
Classifier: Intended Audience :: Science/Research
Classifier: Topic :: Scientific/Engineering :: Bio-Informatics
Requires-Python: >=3.0
License-File: LICENSE.txt
Requires-Dist: sortedcontainers>=2.4.0
Requires-Dist: numpy>=1.26.4
Requires-Dist: pysam>=0.22.1
